{
  "jurisdiction": "TX",
  "law_code": "TN",
  "code_name": "Transp. Code",
  "section_num": "551.001",
  "section_name": "Applicability",
  "division": null,
  "division_title": null,
  "division_range": null,
  "chapter": "551",
  "chapter_title": "Operation of Bicycles & Mopeds, Golf Carts, and Other Low-powered Vehicles",
  "chapter_range": null,
  "article": null,
  "article_title": null,
  "article_range": null,
  "part": null,
  "part_title": null,
  "title": "7",
  "title_title": null,
  "node_tree_path": null,
  "text": "Unless specifically provided otherwise, a provision of this chapter that applies to a person operating a bicycle applies only to a person operating a bicycle on:\n\n(1) a highway; or\n\n(2) a path set aside for the exclusive operation of bicycles.",
  "markdown": "# Transp. Code\n## Title 7\n### Chapter 551. Operation of Bicycles & Mopeds, Golf Carts, and Other Low-powered Vehicles\n##### § 551.001 — Applicability\n\nUnless specifically provided otherwise, a provision of this chapter that applies to a person operating a bicycle applies only to a person operating a bicycle on:\n\n    (1) a highway; or\n\n    (2) a path set aside for the exclusive operation of bicycles.\n\n*Acts 2019, 86th Leg., R.S., Ch. 485 (H.B.2188), Sec. 3, eff. September 1, 2019.*\n",
  "subsections": [
    {
      "label": null,
      "text": "Unless specifically provided otherwise, a provision of this chapter that applies to a person operating a bicycle applies only to a person operating a bicycle on:",
      "depth_em": 0.0
    },
    {
      "label": "1",
      "text": "a highway; or",
      "depth_em": 1.0
    },
    {
      "label": "2",
      "text": "a path set aside for the exclusive operation of bicycles.",
      "depth_em": 1.0
    }
  ],
  "history": {
    "raw": "Acts 2019, 86th Leg., R.S., Ch. 485 (H.B.2188), Sec. 3, eff. September 1, 2019.",
    "action": null,
    "statutes_year": 2019,
    "chapter": null,
    "section": null,
    "bill_number": null,
    "effective_date": "2019-09-01",
    "operative_date": null
  },
  "op_statues": null,
  "op_chapter": null,
  "op_section": null,
  "source_url": "https://texas.public.law/statutes/tex._transp._code_section_551.001",
  "source_path": "data/raw/tx_public_law/TN/551.001.html",
  "content_sha256": "ce52471717792854afeaa28187056b8eb33284aa787e4676fa4bc55ff74ee60a",
  "parsed_at": "2026-05-09T18:32:27+00:00",
  "parser_version": "1"
}
