{
  "jurisdiction": "TX",
  "law_code": "TN",
  "code_name": "Transp. Code",
  "section_num": "724.063",
  "section_name": "Admissibility of Alcohol Concentration or Presence of Substance",
  "division": null,
  "division_title": null,
  "division_range": null,
  "chapter": "724",
  "chapter_title": "Implied Consent",
  "chapter_range": null,
  "article": null,
  "article_title": null,
  "article_range": null,
  "part": null,
  "part_title": null,
  "title": "7",
  "title_title": null,
  "node_tree_path": null,
  "text": "Evidence of alcohol concentration or the presence of a controlled substance, drug, dangerous drug, or other substance obtained by an analysis authorized by Section 724.014 (Person Incapable of Refusal) is admissible in a civil or criminal action.",
  "markdown": "# Transp. Code\n## Title 7\n### Chapter 724. Implied Consent\n##### § 724.063 — Admissibility of Alcohol Concentration or Presence of Substance\n\nEvidence of alcohol concentration or the presence of a controlled substance, drug, dangerous drug, or other substance obtained by an analysis authorized by Section 724.014 (Person Incapable of Refusal) is admissible in a civil or criminal action.\n\n*Acts 1995, 74th Leg., ch. 165, Sec. 1, eff. Sept. 1, 1995. Amended by Acts 1997, 75th Leg., ch. 165, Sec. 30.165, eff. Sept. 1, 1997.*\n",
  "subsections": [
    {
      "label": null,
      "text": "Evidence of alcohol concentration or the presence of a controlled substance, drug, dangerous drug, or other substance obtained by an analysis authorized by Section 724.014 (Person Incapable of Refusal) is admissible in a civil or criminal action.",
      "depth_em": 0.0
    }
  ],
  "history": {
    "raw": "Acts 1995, 74th Leg., ch. 165, Sec. 1, eff. Sept. 1, 1995. Amended by Acts 1997, 75th Leg., ch. 165, Sec. 30.165, eff. Sept. 1, 1997.",
    "action": "Enacted",
    "statutes_year": 1995,
    "chapter": "165",
    "section": "1",
    "bill_number": null,
    "effective_date": "1995-09-01",
    "operative_date": null
  },
  "op_statues": null,
  "op_chapter": null,
  "op_section": null,
  "source_url": "https://texas.public.law/statutes/tex._transp._code_section_724.063",
  "source_path": "data/raw/tx_public_law/TN/724.063.html",
  "content_sha256": "0f71d2742f3c34cb8c3738150f0e3f6cc7927a67ac2638b86ff6441095883072",
  "parsed_at": "2026-05-09T18:32:28+00:00",
  "parser_version": "1"
}
