{
  "jurisdiction": "CA",
  "law_code": "VEH",
  "code_name": "Vehicle Code",
  "section_num": "21051",
  "section_name": null,
  "division": "11",
  "division_title": "RULES OF THE ROAD",
  "division_range": "21000 - 23336",
  "chapter": "1",
  "chapter_title": "Obedience to and Effect of Traffic Laws",
  "chapter_range": "21000 - 21300",
  "article": "2",
  "article_title": "Effect of Traffic Laws",
  "article_range": "21050 - 21070",
  "part": null,
  "part_title": null,
  "title": null,
  "title_title": null,
  "node_tree_path": "15.1.2",
  "text": "The following sections apply to trolley coaches:\n\n(a) Sections 1800, 4000, 4001, 4002, 4003, 4006, 4009, 4150, 4151, 4152, 4153, 4155, 4156, 4158, 4166, 4300 to 4309, inclusive, 4450 to 4454, inclusive, 4457, 4458, 4459, 4460, 4600 to 4610, inclusive, 4750, 4751, 4850, 4851, 4852, 4853, 5000, 5200 to 5205, inclusive, 5904, 6052, 8801, 9254, and 40001 with respect to 4000, relating to original and renewal of registration.\n\n(b) Sections 9250, 9265, 9400, 9406, 9407, 9408, 9550, 9552, 9553, 9554, 9800 to 9808, inclusive, 14901, 42230 to 42233, inclusive, relating to registration and other fees.\n\n(c) Sections 2800, 10851, 10852, 10853, 20001 to 20009, inclusive, 21052, 21053, 21054, 21450 to 21457, inclusive, 21461, 21650, 21651, 21658, 21659, 21700, 21701, 21702, 21703, 21709, 21712, 21750, 21753, 21754, 21755, 21800, 21801, 21802, 21806, 21950, 21951, 22106, 22107, 22108, 22109, 22350, 22351, 22352, 22400, 22450 to 22453, inclusive, 23103, 23104, 23105, 23110, 23152, 23153, 40831, 42002 with respect to 10852 and 10853, and 42004, relating to traffic laws.\n\n(d) Sections 26706, 26707, and 26708, relating to equipment.\n\n(e) Sections 17301, 17302, 17303, 21461, 35000, 35100, 35101, 35105, 35106, 35111, 35550, 35551, 35750, 35751, 35753, 40000.1 to 40000.25, inclusive, 40001, 40003, and 42031, relating to the size, weight, and loading of vehicles.",
  "markdown": "# Vehicle Code\n## Division 11. RULES OF THE ROAD [21000 - 23336]\n### Chapter 1. Obedience to and Effect of Traffic Laws [21000 - 21300]\n#### Article 2. Effect of Traffic Laws [21050 - 21070]\n##### § 21051\n\nThe following sections apply to trolley coaches:\n\n(a) Sections 1800, 4000, 4001, 4002, 4003, 4006, 4009, 4150, 4151, 4152, 4153, 4155, 4156, 4158, 4166, 4300 to 4309, inclusive, 4450 to 4454, inclusive, 4457, 4458, 4459, 4460, 4600 to 4610, inclusive, 4750, 4751, 4850, 4851, 4852, 4853, 5000, 5200 to 5205, inclusive, 5904, 6052, 8801, 9254, and 40001 with respect to 4000, relating to original and renewal of registration.\n\n(b) Sections 9250, 9265, 9400, 9406, 9407, 9408, 9550, 9552, 9553, 9554, 9800 to 9808, inclusive, 14901, 42230 to 42233, inclusive, relating to registration and other fees.\n\n(c) Sections 2800, 10851, 10852, 10853, 20001 to 20009, inclusive, 21052, 21053, 21054, 21450 to 21457, inclusive, 21461, 21650, 21651, 21658, 21659, 21700, 21701, 21702, 21703, 21709, 21712, 21750, 21753, 21754, 21755, 21800, 21801, 21802, 21806, 21950, 21951, 22106, 22107, 22108, 22109, 22350, 22351, 22352, 22400, 22450 to 22453, inclusive, 23103, 23104, 23105, 23110, 23152, 23153, 40831, 42002 with respect to 10852 and 10853, and 42004, relating to traffic laws.\n\n(d) Sections 26706, 26707, and 26708, relating to equipment.\n\n(e) Sections 17301, 17302, 17303, 21461, 35000, 35100, 35101, 35105, 35106, 35111, 35550, 35551, 35750, 35751, 35753, 40000.1 to 40000.25, inclusive, 40001, 40003, and 42031, relating to the size, weight, and loading of vehicles.\n\n*(Amended by Stats. 2007, Ch. 682, Sec. 15. Effective January 1, 2008.)*\n",
  "subsections": [
    {
      "label": null,
      "text": "The following sections apply to trolley coaches:",
      "depth_em": 0.0
    },
    {
      "label": "a",
      "text": "Sections 1800, 4000, 4001, 4002, 4003, 4006, 4009, 4150, 4151, 4152, 4153, 4155, 4156, 4158, 4166, 4300 to 4309, inclusive, 4450 to 4454, inclusive, 4457, 4458, 4459, 4460, 4600 to 4610, inclusive, 4750, 4751, 4850, 4851, 4852, 4853, 5000, 5200 to 5205, inclusive, 5904, 6052, 8801, 9254, and 40001 with respect to 4000, relating to original and renewal of registration.",
      "depth_em": 0.0
    },
    {
      "label": "b",
      "text": "Sections 9250, 9265, 9400, 9406, 9407, 9408, 9550, 9552, 9553, 9554, 9800 to 9808, inclusive, 14901, 42230 to 42233, inclusive, relating to registration and other fees.",
      "depth_em": 0.0
    },
    {
      "label": "c",
      "text": "Sections 2800, 10851, 10852, 10853, 20001 to 20009, inclusive, 21052, 21053, 21054, 21450 to 21457, inclusive, 21461, 21650, 21651, 21658, 21659, 21700, 21701, 21702, 21703, 21709, 21712, 21750, 21753, 21754, 21755, 21800, 21801, 21802, 21806, 21950, 21951, 22106, 22107, 22108, 22109, 22350, 22351, 22352, 22400, 22450 to 22453, inclusive, 23103, 23104, 23105, 23110, 23152, 23153, 40831, 42002 with respect to 10852 and 10853, and 42004, relating to traffic laws.",
      "depth_em": 0.0
    },
    {
      "label": "d",
      "text": "Sections 26706, 26707, and 26708, relating to equipment.",
      "depth_em": 0.0
    },
    {
      "label": "e",
      "text": "Sections 17301, 17302, 17303, 21461, 35000, 35100, 35101, 35105, 35106, 35111, 35550, 35551, 35750, 35751, 35753, 40000.1 to 40000.25, inclusive, 40001, 40003, and 42031, relating to the size, weight, and loading of vehicles.",
      "depth_em": 0.0
    }
  ],
  "history": {
    "raw": "(Amended by Stats. 2007, Ch. 682, Sec. 15. Effective January 1, 2008.)",
    "action": "Amended",
    "statutes_year": 2007,
    "chapter": "682",
    "section": "15",
    "bill_number": null,
    "effective_date": "2008-01-01",
    "operative_date": null
  },
  "op_statues": "2007",
  "op_chapter": "682",
  "op_section": "15",
  "source_url": "https://leginfo.legislature.ca.gov/faces/codes_displaySection.xhtml?sectionNum=21051.&lawCode=VEH",
  "source_path": "data/raw/ca_leginfo_pages/VEH/21051.html",
  "content_sha256": "53a9f7afbeda6ea26c9aa37c4511f39cac0dc8133f2f3ea04cfd00dc056fa2d8",
  "parsed_at": "2026-05-09T18:32:19+00:00",
  "parser_version": "1"
}
