{
  "jurisdiction": "CA",
  "law_code": "VEH",
  "code_name": "Vehicle Code",
  "section_num": "21100.4",
  "section_name": null,
  "division": "11",
  "division_title": "RULES OF THE ROAD",
  "division_range": "21000 - 23336",
  "chapter": "1",
  "chapter_title": "Obedience to and Effect of Traffic Laws",
  "chapter_range": "21000 - 21300",
  "article": "3",
  "article_title": "Local Regulation",
  "article_range": "21100 - 21118",
  "part": null,
  "part_title": null,
  "title": null,
  "title_title": null,
  "node_tree_path": "15.1.3",
  "text": "(a) (1) A magistrate presented with the affidavit of a peace officer or a designated local transportation officer establishing reasonable cause to believe that a vehicle, described by vehicle type and license number, is being operated as a taxicab or other passenger vehicle for hire in violation of licensing requirements adopted by a local authority under subdivision (b) of Section 21100 shall issue a warrant or order authorizing the peace officer or designated local transportation officer to immediately seize and cause the removal of the vehicle. As used in this section, “designated local transportation officer” means any local public officer employed by a local authority to investigate and enforce local taxicab and vehicle for hire laws and regulations.\n\n(2) The warrant or court order may be entered into a computerized database.\n\n(3) A vehicle so impounded may be impounded for a period not to exceed 30 days.\n\n(4) The impounding agency, within two working days of impoundment, shall send a notice by certified mail, return receipt requested, to the legal owner of the vehicle, at an address obtained from the department, informing the owner that the vehicle has been impounded and providing the owner with a copy of the warrant or court order. Failure to notify the legal owner within two working days shall prohibit the impounding agency from charging for more than 15 days’ impoundment when a legal owner redeems the impounded vehicle. The law enforcement agency shall be open to issue a release to the registered owner or legal owner, or the agent of either, whenever the agency is open to serve the public for regular, nonemergency business.\n\n(b) (1) An impounding agency shall release a vehicle to the registered owner or his or her agent prior to the end of the impoundment period and without the permission of the magistrate authorizing the vehicle’s seizure under any of the following circumstances:\n\n(A) When the vehicle is a stolen vehicle.\n\n(B) When the vehicle was seized under this section for an offense that does not authorize the seizure of the vehicle.\n\n(C) When the vehicle is a rental car.\n\n(2) A vehicle may not be released under this subdivision, except upon presentation of the registered owner’s or agent’s currently valid license to operate the vehicle under the licensing requirements adopted by the local authority under subdivision (b) of Section 21100, and proof of current vehicle registration, or upon order of the court.\n\n(c) (1) Whenever a vehicle is impounded under this section, the magistrate ordering the storage shall provide the vehicle’s registered and legal owners of record, or their agents, with the opportunity for a poststorage hearing to determine the validity of the storage.\n\n(2) A notice of the storage shall be mailed or personally delivered to the registered and legal owners within 48 hours after issuance of the warrant or court order, excluding weekends and holidays, by the person or agency executing the warrant or court order, and shall include all of the following information:\n\n(A) The name, address, and telephone number of the agency providing the notice.\n\n(B) The location of the place of storage and a description of the vehicle, which shall include, if available, the name or make, the manufacturer, the license plate number, and the mileage of the vehicle.\n\n(C) A copy of the warrant or court order and the peace officer’s affidavit, as described in subdivision (a).\n\n(D) A statement that, in order to receive their poststorage hearing, the owners, or their agents, are required to request the hearing from the magistrate issuing the warrant or court order in person, in writing, or by telephone, within 10 days of the date of the notice.\n\n(3) The poststorage hearing shall be conducted within two court days after receipt of the request for the hearing.\n\n(4) At the hearing, the magistrate may order the vehicle released if he or she finds any of the circumstances described in subdivision (b) or (e) that allow release of a vehicle by the impounding agency.\n\n(5) Failure of either the registered or legal owner, or his or her agent, to request, or to attend, a scheduled hearing satisfies the poststorage hearing requirement.\n\n(6) The agency employing the peace officer or designated local transportation officer who caused the magistrate to issue the warrant or court order shall be responsible for the costs incurred for towing and storage if it is determined in the poststorage hearing that reasonable grounds for the storage are not established.\n\n(d) The registered owner or his or her agent is responsible for all towing and storage charges related to the impoundment, and any administrative charges authorized under Section 22850.5.\n\n(e) A vehicle removed and seized under subdivision (a) shall be released to the legal owner of the vehicle or the legal owner’s agent prior to the end of the impoundment period and without the permission of the magistrate authorizing the seizure of the vehicle if all of the following conditions are met:\n\n(1) The legal owner is a motor vehicle dealer, bank, credit union, acceptance corporation, or other licensed financial institution legally operating in this state or is another person, not the registered owner, holding a security interest in the vehicle.\n\n(2) (A) The legal owner or the legal owner’s agent pays all towing and storage fees related to the seizure of the vehicle. A lien sale processing fee shall not be charged to the legal owner who redeems the vehicle prior to the 15th day of impoundment. Neither the impounding authority nor any person having possession of the vehicle shall collect from the legal owner of the type specified in paragraph (1), or the legal owner’s agent, any administrative charges imposed pursuant to Section 22850.5 unless the legal owner voluntarily requested a poststorage hearing.\n\n(B) A person operating or in charge of a storage facility where vehicles are stored pursuant to this section shall accept a valid bank credit card or cash for payment of towing, storage, and related fees by a legal or registered owner or the owner’s agent claiming the vehicle. A credit card shall be in the name of the person presenting the card. “Credit card” means “credit card” as defined in subdivision (a) of Section 1747.02 of the Civil Code, except, for the purposes of this section, credit card does not include a credit card issued by a retail seller.\n\n(C) A person operating or in charge of a storage facility described in subparagraph (B) who violates subparagraph (B) shall be civilly liable to the owner of the vehicle or to the person who tendered the fees for four times the amount of the towing, storage, and related fees, but not to exceed five hundred dollars ($500).\n\n(D) A person operating or in charge of a storage facility described in subparagraph (B) shall have sufficient funds on the premises of the primary storage facility during normal business hours to accommodate, and make change in, a reasonable monetary transaction.\n\n(E) Credit charges for towing and storage services shall comply with Section 1748.1 of the Civil Code. Law enforcement agencies may include the costs of providing for payment by credit when making agreements with towing companies on rates.\n\n(3) (A) The legal owner or the legal owner’s agent presents to the law enforcement agency or impounding agency, or any person acting on behalf of those agencies, a copy of the assignment, as defined in subdivision (b) of Section 7500.1 of the Business and Professions Code; a release from the one responsible governmental agency, only if required by the agency; a government-issued photographic identification card; and any one of the following as determined by the legal owner or the legal owner’s agent: a certificate of repossession for the vehicle, a security agreement for the vehicle, or title, whether paper or electronic, showing proof of legal ownership for the vehicle. The law enforcement agency, impounding agency, or any other governmental agency, or any person acting on behalf of those agencies, shall not require the presentation of any other documents.\n\n(B) The legal owner or the legal owner’s agent presents to the person in possession of the vehicle, or any person acting on behalf of the person in possession, a copy of the assignment, as defined in subdivision (b) of Section 7500.1 of the Business and Professions Code; a release from the one responsible governmental agency, only if required by the agency; a government-issued photographic identification card; and any one of the following as determined by the legal owner or the legal owner’s agent: a certificate of repossession for the vehicle, a security agreement for the vehicle, or title, whether paper or electronic, showing proof of legal ownership for the vehicle. The person in possession of the vehicle, or any person acting on behalf of the person in possession, shall not require the presentation of any other documents.\n\n(C) All presented documents may be originals, photocopies, or facsimile copies, or may be transmitted electronically. The law enforcement agency, impounding agency, or any person in possession of the vehicle, or anyone acting on behalf of them, shall not require any documents to be notarized. The law enforcement agency, impounding agency, or any person acting on behalf of those agencies, may require the agent of the legal owner to produce a photocopy or facsimile copy of its repossession agency license or registration issued pursuant to Chapter 11 (commencing with Section 7500) of Division 3 of the Business and Professions Code, or to demonstrate, to the satisfaction of the law enforcement agency, impounding agency, or any person in possession of the vehicle, or anyone acting on behalf of them, that the agent is exempt from licensure pursuant to Section 7500.2 or 7500.3 of the Business and Professions Code.\n\n(D) An administrative cost authorized under subdivision (a) of Section 22850.5 shall not be charged to the legal owner of the type specified in paragraph (1) who redeems the vehicle unless the legal owner voluntarily requests a poststorage hearing. A city, county, city and county, or state agency shall not require a legal owner or a legal owner’s agent to request a poststorage hearing as a requirement for release of the vehicle to the legal owner or the legal owner’s agent. The law enforcement agency, impounding agency, or any other governmental agency, or any person acting on behalf of those agencies, shall not require any documents other than those specified in this paragraph. The law enforcement agency, impounding agency, or other governmental agency, or any person acting on behalf of those agencies, may not require any documents to be notarized. The legal owner or the legal owner’s agent shall be given a copy of any documents he or she is required to sign, except for a vehicle evidentiary hold logbook. The law enforcement agency, impounding agency, or any person acting on behalf of those agencies, or any person in possession of the vehicle, may photocopy and retain the copies of any documents presented by the legal owner or legal owner’s agent.\n\n(4) A failure by a storage facility to comply with any applicable conditions set forth in this subdivision shall not affect the right of the legal owner or the legal owner’s agent to retrieve the vehicle, provided all conditions required of the legal owner or legal owner’s agent under this subdivision are satisfied.\n\n(f) (1) A legal owner or the legal owner’s agent that obtains release of the vehicle pursuant to subdivision (e) shall not release the vehicle to the registered owner of the vehicle or the person who was listed as the registered owner when the vehicle was impounded or any agents of the registered owner until the termination of the impoundment period.\n\n(2) The legal owner or the legal owner’s agent shall not relinquish the vehicle to the registered owner or the person who was listed as the registered owner when the vehicle was impounded until the registered owner or that owner’s agent presents his or her valid driver’s license or valid temporary driver’s license, and an operator’s license that is in compliance with the licensing requirements adopted by the local authority under subdivision (b) of Section 21100, to the legal owner or the legal owner’s agent. The legal owner or the legal owner’s agent or the person in possession of the vehicle shall make every reasonable effort to ensure that the licenses presented are valid and possession of the vehicle will not be given to the driver who was involved in the original impoundment proceeding until the expiration of the impoundment period.\n\n(3) Prior to relinquishing the vehicle, the legal owner may require the registered owner to pay all towing and storage charges related to the impoundment and the administrative charges authorized under Section 22850.5 that were incurred by the legal owner in connection with obtaining the custody of the vehicle.\n\n(4) Any legal owner who knowingly releases or causes the release of a vehicle to a registered owner or the person in possession of the vehicle at the time of the impoundment or any agent of the registered owner in violation of this subdivision shall be guilty of a misdemeanor and subject to a civil penalty in the amount of two thousand dollars ($2,000).\n\n(5) The legal owner, registered owner, or person in possession of the vehicle shall not change or attempt to change the name of the legal owner or the registered owner on the records of the department until the vehicle is released from the impoundment.\n\n(g) Notwithstanding any other provision of this section, the registered owner and not the legal owner shall remain responsible for any towing and storage charges related to the impoundment and the administrative charges authorized under Section 22850.5 and any parking fines, penalties, and administrative fees incurred by the registered owner.\n\n(h) The law enforcement agency and the impounding agency, including any storage facility acting on behalf of the law enforcement agency or impounding agency, shall comply with this section and shall not be liable to the registered owner for the improper release of the vehicle to the legal owner or the legal owner’s agent if the release complies with this section. The legal owner shall indemnify and hold harmless a storage facility from any claims arising out of the release of the vehicle to the legal owner or the legal owner’s agent and from any damage to the vehicle after its release, including the reasonable costs associated with defending any such claims. A law enforcement agency shall not refuse to issue a release to a legal owner or the agent of a legal owner on the grounds that it previously issued a release.",
  "markdown": "# Vehicle Code\n## Division 11. RULES OF THE ROAD [21000 - 23336]\n### Chapter 1. Obedience to and Effect of Traffic Laws [21000 - 21300]\n#### Article 3. Local Regulation [21100 - 21118]\n##### § 21100.4\n\n(a) (1) A magistrate presented with the affidavit of a peace officer or a designated local transportation officer establishing reasonable cause to believe that a vehicle, described by vehicle type and license number, is being operated as a taxicab or other passenger vehicle for hire in violation of licensing requirements adopted by a local authority under subdivision (b) of Section 21100 shall issue a warrant or order authorizing the peace officer or designated local transportation officer to immediately seize and cause the removal of the vehicle. As used in this section, “designated local transportation officer” means any local public officer employed by a local authority to investigate and enforce local taxicab and vehicle for hire laws and regulations.\n\n    (2) The warrant or court order may be entered into a computerized database.\n\n    (3) A vehicle so impounded may be impounded for a period not to exceed 30 days.\n\n    (4) The impounding agency, within two working days of impoundment, shall send a notice by certified mail, return receipt requested, to the legal owner of the vehicle, at an address obtained from the department, informing the owner that the vehicle has been impounded and providing the owner with a copy of the warrant or court order. Failure to notify the legal owner within two working days shall prohibit the impounding agency from charging for more than 15 days’ impoundment when a legal owner redeems the impounded vehicle. The law enforcement agency shall be open to issue a release to the registered owner or legal owner, or the agent of either, whenever the agency is open to serve the public for regular, nonemergency business.\n\n(b) (1) An impounding agency shall release a vehicle to the registered owner or his or her agent prior to the end of the impoundment period and without the permission of the magistrate authorizing the vehicle’s seizure under any of the following circumstances:\n\n        (A) When the vehicle is a stolen vehicle.\n\n        (B) When the vehicle was seized under this section for an offense that does not authorize the seizure of the vehicle.\n\n        (C) When the vehicle is a rental car.\n\n    (2) A vehicle may not be released under this subdivision, except upon presentation of the registered owner’s or agent’s currently valid license to operate the vehicle under the licensing requirements adopted by the local authority under subdivision (b) of Section 21100, and proof of current vehicle registration, or upon order of the court.\n\n(c) (1) Whenever a vehicle is impounded under this section, the magistrate ordering the storage shall provide the vehicle’s registered and legal owners of record, or their agents, with the opportunity for a poststorage hearing to determine the validity of the storage.\n\n    (2) A notice of the storage shall be mailed or personally delivered to the registered and legal owners within 48 hours after issuance of the warrant or court order, excluding weekends and holidays, by the person or agency executing the warrant or court order, and shall include all of the following information:\n\n        (A) The name, address, and telephone number of the agency providing the notice.\n\n        (B) The location of the place of storage and a description of the vehicle, which shall include, if available, the name or make, the manufacturer, the license plate number, and the mileage of the vehicle.\n\n        (C) A copy of the warrant or court order and the peace officer’s affidavit, as described in subdivision (a).\n\n        (D) A statement that, in order to receive their poststorage hearing, the owners, or their agents, are required to request the hearing from the magistrate issuing the warrant or court order in person, in writing, or by telephone, within 10 days of the date of the notice.\n\n    (3) The poststorage hearing shall be conducted within two court days after receipt of the request for the hearing.\n\n    (4) At the hearing, the magistrate may order the vehicle released if he or she finds any of the circumstances described in subdivision (b) or (e) that allow release of a vehicle by the impounding agency.\n\n    (5) Failure of either the registered or legal owner, or his or her agent, to request, or to attend, a scheduled hearing satisfies the poststorage hearing requirement.\n\n    (6) The agency employing the peace officer or designated local transportation officer who caused the magistrate to issue the warrant or court order shall be responsible for the costs incurred for towing and storage if it is determined in the poststorage hearing that reasonable grounds for the storage are not established.\n\n(d) The registered owner or his or her agent is responsible for all towing and storage charges related to the impoundment, and any administrative charges authorized under Section 22850.5.\n\n(e) A vehicle removed and seized under subdivision (a) shall be released to the legal owner of the vehicle or the legal owner’s agent prior to the end of the impoundment period and without the permission of the magistrate authorizing the seizure of the vehicle if all of the following conditions are met:\n\n    (1) The legal owner is a motor vehicle dealer, bank, credit union, acceptance corporation, or other licensed financial institution legally operating in this state or is another person, not the registered owner, holding a security interest in the vehicle.\n\n    (2) (A) The legal owner or the legal owner’s agent pays all towing and storage fees related to the seizure of the vehicle. A lien sale processing fee shall not be charged to the legal owner who redeems the vehicle prior to the 15th day of impoundment. Neither the impounding authority nor any person having possession of the vehicle shall collect from the legal owner of the type specified in paragraph (1), or the legal owner’s agent, any administrative charges imposed pursuant to Section 22850.5 unless the legal owner voluntarily requested a poststorage hearing.\n\n        (B) A person operating or in charge of a storage facility where vehicles are stored pursuant to this section shall accept a valid bank credit card or cash for payment of towing, storage, and related fees by a legal or registered owner or the owner’s agent claiming the vehicle. A credit card shall be in the name of the person presenting the card. “Credit card” means “credit card” as defined in subdivision (a) of Section 1747.02 of the Civil Code, except, for the purposes of this section, credit card does not include a credit card issued by a retail seller.\n\n        (C) A person operating or in charge of a storage facility described in subparagraph (B) who violates subparagraph (B) shall be civilly liable to the owner of the vehicle or to the person who tendered the fees for four times the amount of the towing, storage, and related fees, but not to exceed five hundred dollars ($500).\n\n        (D) A person operating or in charge of a storage facility described in subparagraph (B) shall have sufficient funds on the premises of the primary storage facility during normal business hours to accommodate, and make change in, a reasonable monetary transaction.\n\n        (E) Credit charges for towing and storage services shall comply with Section 1748.1 of the Civil Code. Law enforcement agencies may include the costs of providing for payment by credit when making agreements with towing companies on rates.\n\n    (3) (A) The legal owner or the legal owner’s agent presents to the law enforcement agency or impounding agency, or any person acting on behalf of those agencies, a copy of the assignment, as defined in subdivision (b) of Section 7500.1 of the Business and Professions Code; a release from the one responsible governmental agency, only if required by the agency; a government-issued photographic identification card; and any one of the following as determined by the legal owner or the legal owner’s agent: a certificate of repossession for the vehicle, a security agreement for the vehicle, or title, whether paper or electronic, showing proof of legal ownership for the vehicle. The law enforcement agency, impounding agency, or any other governmental agency, or any person acting on behalf of those agencies, shall not require the presentation of any other documents.\n\n        (B) The legal owner or the legal owner’s agent presents to the person in possession of the vehicle, or any person acting on behalf of the person in possession, a copy of the assignment, as defined in subdivision (b) of Section 7500.1 of the Business and Professions Code; a release from the one responsible governmental agency, only if required by the agency; a government-issued photographic identification card; and any one of the following as determined by the legal owner or the legal owner’s agent: a certificate of repossession for the vehicle, a security agreement for the vehicle, or title, whether paper or electronic, showing proof of legal ownership for the vehicle. The person in possession of the vehicle, or any person acting on behalf of the person in possession, shall not require the presentation of any other documents.\n\n        (C) All presented documents may be originals, photocopies, or facsimile copies, or may be transmitted electronically. The law enforcement agency, impounding agency, or any person in possession of the vehicle, or anyone acting on behalf of them, shall not require any documents to be notarized. The law enforcement agency, impounding agency, or any person acting on behalf of those agencies, may require the agent of the legal owner to produce a photocopy or facsimile copy of its repossession agency license or registration issued pursuant to Chapter 11 (commencing with Section 7500) of Division 3 of the Business and Professions Code, or to demonstrate, to the satisfaction of the law enforcement agency, impounding agency, or any person in possession of the vehicle, or anyone acting on behalf of them, that the agent is exempt from licensure pursuant to Section 7500.2 or 7500.3 of the Business and Professions Code.\n\n        (D) An administrative cost authorized under subdivision (a) of Section 22850.5 shall not be charged to the legal owner of the type specified in paragraph (1) who redeems the vehicle unless the legal owner voluntarily requests a poststorage hearing. A city, county, city and county, or state agency shall not require a legal owner or a legal owner’s agent to request a poststorage hearing as a requirement for release of the vehicle to the legal owner or the legal owner’s agent. The law enforcement agency, impounding agency, or any other governmental agency, or any person acting on behalf of those agencies, shall not require any documents other than those specified in this paragraph. The law enforcement agency, impounding agency, or other governmental agency, or any person acting on behalf of those agencies, may not require any documents to be notarized. The legal owner or the legal owner’s agent shall be given a copy of any documents he or she is required to sign, except for a vehicle evidentiary hold logbook. The law enforcement agency, impounding agency, or any person acting on behalf of those agencies, or any person in possession of the vehicle, may photocopy and retain the copies of any documents presented by the legal owner or legal owner’s agent.\n\n    (4) A failure by a storage facility to comply with any applicable conditions set forth in this subdivision shall not affect the right of the legal owner or the legal owner’s agent to retrieve the vehicle, provided all conditions required of the legal owner or legal owner’s agent under this subdivision are satisfied.\n\n(f) (1) A legal owner or the legal owner’s agent that obtains release of the vehicle pursuant to subdivision (e) shall not release the vehicle to the registered owner of the vehicle or the person who was listed as the registered owner when the vehicle was impounded or any agents of the registered owner until the termination of the impoundment period.\n\n    (2) The legal owner or the legal owner’s agent shall not relinquish the vehicle to the registered owner or the person who was listed as the registered owner when the vehicle was impounded until the registered owner or that owner’s agent presents his or her valid driver’s license or valid temporary driver’s license, and an operator’s license that is in compliance with the licensing requirements adopted by the local authority under subdivision (b) of Section 21100, to the legal owner or the legal owner’s agent. The legal owner or the legal owner’s agent or the person in possession of the vehicle shall make every reasonable effort to ensure that the licenses presented are valid and possession of the vehicle will not be given to the driver who was involved in the original impoundment proceeding until the expiration of the impoundment period.\n\n    (3) Prior to relinquishing the vehicle, the legal owner may require the registered owner to pay all towing and storage charges related to the impoundment and the administrative charges authorized under Section 22850.5 that were incurred by the legal owner in connection with obtaining the custody of the vehicle.\n\n    (4) Any legal owner who knowingly releases or causes the release of a vehicle to a registered owner or the person in possession of the vehicle at the time of the impoundment or any agent of the registered owner in violation of this subdivision shall be guilty of a misdemeanor and subject to a civil penalty in the amount of two thousand dollars ($2,000).\n\n    (5) The legal owner, registered owner, or person in possession of the vehicle shall not change or attempt to change the name of the legal owner or the registered owner on the records of the department until the vehicle is released from the impoundment.\n\n(g) Notwithstanding any other provision of this section, the registered owner and not the legal owner shall remain responsible for any towing and storage charges related to the impoundment and the administrative charges authorized under Section 22850.5 and any parking fines, penalties, and administrative fees incurred by the registered owner.\n\n(h) The law enforcement agency and the impounding agency, including any storage facility acting on behalf of the law enforcement agency or impounding agency, shall comply with this section and shall not be liable to the registered owner for the improper release of the vehicle to the legal owner or the legal owner’s agent if the release complies with this section. The legal owner shall indemnify and hold harmless a storage facility from any claims arising out of the release of the vehicle to the legal owner or the legal owner’s agent and from any damage to the vehicle after its release, including the reasonable costs associated with defending any such claims. A law enforcement agency shall not refuse to issue a release to a legal owner or the agent of a legal owner on the grounds that it previously issued a release.\n\n*(Amended by Stats. 2011, Ch. 536, Sec. 14. (AB 957) Effective January 1, 2012.)*\n",
  "subsections": [
    {
      "label": "a",
      "text": "(1) A magistrate presented with the affidavit of a peace officer or a designated local transportation officer establishing reasonable cause to believe that a vehicle, described by vehicle type and license number, is being operated as a taxicab or other passenger vehicle for hire in violation of licensing requirements adopted by a local authority under subdivision (b) of Section 21100 shall issue a warrant or order authorizing the peace officer or designated local transportation officer to immediately seize and cause the removal of the vehicle. As used in this section, “designated local transportation officer” means any local public officer employed by a local authority to investigate and enforce local taxicab and vehicle for hire laws and regulations.",
      "depth_em": 0.0
    },
    {
      "label": "2",
      "text": "The warrant or court order may be entered into a computerized database.",
      "depth_em": 1.0
    },
    {
      "label": "3",
      "text": "A vehicle so impounded may be impounded for a period not to exceed 30 days.",
      "depth_em": 1.0
    },
    {
      "label": "4",
      "text": "The impounding agency, within two working days of impoundment, shall send a notice by certified mail, return receipt requested, to the legal owner of the vehicle, at an address obtained from the department, informing the owner that the vehicle has been impounded and providing the owner with a copy of the warrant or court order. Failure to notify the legal owner within two working days shall prohibit the impounding agency from charging for more than 15 days’ impoundment when a legal owner redeems the impounded vehicle. The law enforcement agency shall be open to issue a release to the registered owner or legal owner, or the agent of either, whenever the agency is open to serve the public for regular, nonemergency business.",
      "depth_em": 1.0
    },
    {
      "label": "b",
      "text": "(1) An impounding agency shall release a vehicle to the registered owner or his or her agent prior to the end of the impoundment period and without the permission of the magistrate authorizing the vehicle’s seizure under any of the following circumstances:",
      "depth_em": 0.0
    },
    {
      "label": "A",
      "text": "When the vehicle is a stolen vehicle.",
      "depth_em": 2.5
    },
    {
      "label": "B",
      "text": "When the vehicle was seized under this section for an offense that does not authorize the seizure of the vehicle.",
      "depth_em": 2.5
    },
    {
      "label": "C",
      "text": "When the vehicle is a rental car.",
      "depth_em": 2.5
    },
    {
      "label": "2",
      "text": "A vehicle may not be released under this subdivision, except upon presentation of the registered owner’s or agent’s currently valid license to operate the vehicle under the licensing requirements adopted by the local authority under subdivision (b) of Section 21100, and proof of current vehicle registration, or upon order of the court.",
      "depth_em": 1.0
    },
    {
      "label": "c",
      "text": "(1) Whenever a vehicle is impounded under this section, the magistrate ordering the storage shall provide the vehicle’s registered and legal owners of record, or their agents, with the opportunity for a poststorage hearing to determine the validity of the storage.",
      "depth_em": 0.0
    },
    {
      "label": "2",
      "text": "A notice of the storage shall be mailed or personally delivered to the registered and legal owners within 48 hours after issuance of the warrant or court order, excluding weekends and holidays, by the person or agency executing the warrant or court order, and shall include all of the following information:",
      "depth_em": 1.0
    },
    {
      "label": "A",
      "text": "The name, address, and telephone number of the agency providing the notice.",
      "depth_em": 2.5
    },
    {
      "label": "B",
      "text": "The location of the place of storage and a description of the vehicle, which shall include, if available, the name or make, the manufacturer, the license plate number, and the mileage of the vehicle.",
      "depth_em": 2.5
    },
    {
      "label": "C",
      "text": "A copy of the warrant or court order and the peace officer’s affidavit, as described in subdivision (a).",
      "depth_em": 2.5
    },
    {
      "label": "D",
      "text": "A statement that, in order to receive their poststorage hearing, the owners, or their agents, are required to request the hearing from the magistrate issuing the warrant or court order in person, in writing, or by telephone, within 10 days of the date of the notice.",
      "depth_em": 2.5
    },
    {
      "label": "3",
      "text": "The poststorage hearing shall be conducted within two court days after receipt of the request for the hearing.",
      "depth_em": 1.0
    },
    {
      "label": "4",
      "text": "At the hearing, the magistrate may order the vehicle released if he or she finds any of the circumstances described in subdivision (b) or (e) that allow release of a vehicle by the impounding agency.",
      "depth_em": 1.0
    },
    {
      "label": "5",
      "text": "Failure of either the registered or legal owner, or his or her agent, to request, or to attend, a scheduled hearing satisfies the poststorage hearing requirement.",
      "depth_em": 1.0
    },
    {
      "label": "6",
      "text": "The agency employing the peace officer or designated local transportation officer who caused the magistrate to issue the warrant or court order shall be responsible for the costs incurred for towing and storage if it is determined in the poststorage hearing that reasonable grounds for the storage are not established.",
      "depth_em": 1.0
    },
    {
      "label": "d",
      "text": "The registered owner or his or her agent is responsible for all towing and storage charges related to the impoundment, and any administrative charges authorized under Section 22850.5.",
      "depth_em": 0.0
    },
    {
      "label": "e",
      "text": "A vehicle removed and seized under subdivision (a) shall be released to the legal owner of the vehicle or the legal owner’s agent prior to the end of the impoundment period and without the permission of the magistrate authorizing the seizure of the vehicle if all of the following conditions are met:",
      "depth_em": 0.0
    },
    {
      "label": "1",
      "text": "The legal owner is a motor vehicle dealer, bank, credit union, acceptance corporation, or other licensed financial institution legally operating in this state or is another person, not the registered owner, holding a security interest in the vehicle.",
      "depth_em": 1.0
    },
    {
      "label": "2",
      "text": "(A) The legal owner or the legal owner’s agent pays all towing and storage fees related to the seizure of the vehicle. A lien sale processing fee shall not be charged to the legal owner who redeems the vehicle prior to the 15th day of impoundment. Neither the impounding authority nor any person having possession of the vehicle shall collect from the legal owner of the type specified in paragraph (1), or the legal owner’s agent, any administrative charges imposed pursuant to Section 22850.5 unless the legal owner voluntarily requested a poststorage hearing.",
      "depth_em": 1.0
    },
    {
      "label": "B",
      "text": "A person operating or in charge of a storage facility where vehicles are stored pursuant to this section shall accept a valid bank credit card or cash for payment of towing, storage, and related fees by a legal or registered owner or the owner’s agent claiming the vehicle. A credit card shall be in the name of the person presenting the card. “Credit card” means “credit card” as defined in subdivision (a) of Section 1747.02 of the Civil Code, except, for the purposes of this section, credit card does not include a credit card issued by a retail seller.",
      "depth_em": 2.5
    },
    {
      "label": "C",
      "text": "A person operating or in charge of a storage facility described in subparagraph (B) who violates subparagraph (B) shall be civilly liable to the owner of the vehicle or to the person who tendered the fees for four times the amount of the towing, storage, and related fees, but not to exceed five hundred dollars ($500).",
      "depth_em": 2.5
    },
    {
      "label": "D",
      "text": "A person operating or in charge of a storage facility described in subparagraph (B) shall have sufficient funds on the premises of the primary storage facility during normal business hours to accommodate, and make change in, a reasonable monetary transaction.",
      "depth_em": 2.5
    },
    {
      "label": "E",
      "text": "Credit charges for towing and storage services shall comply with Section 1748.1 of the Civil Code. Law enforcement agencies may include the costs of providing for payment by credit when making agreements with towing companies on rates.",
      "depth_em": 2.5
    },
    {
      "label": "3",
      "text": "(A) The legal owner or the legal owner’s agent presents to the law enforcement agency or impounding agency, or any person acting on behalf of those agencies, a copy of the assignment, as defined in subdivision (b) of Section 7500.1 of the Business and Professions Code; a release from the one responsible governmental agency, only if required by the agency; a government-issued photographic identification card; and any one of the following as determined by the legal owner or the legal owner’s agent: a certificate of repossession for the vehicle, a security agreement for the vehicle, or title, whether paper or electronic, showing proof of legal ownership for the vehicle. The law enforcement agency, impounding agency, or any other governmental agency, or any person acting on behalf of those agencies, shall not require the presentation of any other documents.",
      "depth_em": 1.0
    },
    {
      "label": "B",
      "text": "The legal owner or the legal owner’s agent presents to the person in possession of the vehicle, or any person acting on behalf of the person in possession, a copy of the assignment, as defined in subdivision (b) of Section 7500.1 of the Business and Professions Code; a release from the one responsible governmental agency, only if required by the agency; a government-issued photographic identification card; and any one of the following as determined by the legal owner or the legal owner’s agent: a certificate of repossession for the vehicle, a security agreement for the vehicle, or title, whether paper or electronic, showing proof of legal ownership for the vehicle. The person in possession of the vehicle, or any person acting on behalf of the person in possession, shall not require the presentation of any other documents.",
      "depth_em": 2.5
    },
    {
      "label": "C",
      "text": "All presented documents may be originals, photocopies, or facsimile copies, or may be transmitted electronically. The law enforcement agency, impounding agency, or any person in possession of the vehicle, or anyone acting on behalf of them, shall not require any documents to be notarized. The law enforcement agency, impounding agency, or any person acting on behalf of those agencies, may require the agent of the legal owner to produce a photocopy or facsimile copy of its repossession agency license or registration issued pursuant to Chapter 11 (commencing with Section 7500) of Division 3 of the Business and Professions Code, or to demonstrate, to the satisfaction of the law enforcement agency, impounding agency, or any person in possession of the vehicle, or anyone acting on behalf of them, that the agent is exempt from licensure pursuant to Section 7500.2 or 7500.3 of the Business and Professions Code.",
      "depth_em": 2.5
    },
    {
      "label": "D",
      "text": "An administrative cost authorized under subdivision (a) of Section 22850.5 shall not be charged to the legal owner of the type specified in paragraph (1) who redeems the vehicle unless the legal owner voluntarily requests a poststorage hearing. A city, county, city and county, or state agency shall not require a legal owner or a legal owner’s agent to request a poststorage hearing as a requirement for release of the vehicle to the legal owner or the legal owner’s agent. The law enforcement agency, impounding agency, or any other governmental agency, or any person acting on behalf of those agencies, shall not require any documents other than those specified in this paragraph. The law enforcement agency, impounding agency, or other governmental agency, or any person acting on behalf of those agencies, may not require any documents to be notarized. The legal owner or the legal owner’s agent shall be given a copy of any documents he or she is required to sign, except for a vehicle evidentiary hold logbook. The law enforcement agency, impounding agency, or any person acting on behalf of those agencies, or any person in possession of the vehicle, may photocopy and retain the copies of any documents presented by the legal owner or legal owner’s agent.",
      "depth_em": 2.5
    },
    {
      "label": "4",
      "text": "A failure by a storage facility to comply with any applicable conditions set forth in this subdivision shall not affect the right of the legal owner or the legal owner’s agent to retrieve the vehicle, provided all conditions required of the legal owner or legal owner’s agent under this subdivision are satisfied.",
      "depth_em": 1.0
    },
    {
      "label": "f",
      "text": "(1) A legal owner or the legal owner’s agent that obtains release of the vehicle pursuant to subdivision (e) shall not release the vehicle to the registered owner of the vehicle or the person who was listed as the registered owner when the vehicle was impounded or any agents of the registered owner until the termination of the impoundment period.",
      "depth_em": 0.0
    },
    {
      "label": "2",
      "text": "The legal owner or the legal owner’s agent shall not relinquish the vehicle to the registered owner or the person who was listed as the registered owner when the vehicle was impounded until the registered owner or that owner’s agent presents his or her valid driver’s license or valid temporary driver’s license, and an operator’s license that is in compliance with the licensing requirements adopted by the local authority under subdivision (b) of Section 21100, to the legal owner or the legal owner’s agent. The legal owner or the legal owner’s agent or the person in possession of the vehicle shall make every reasonable effort to ensure that the licenses presented are valid and possession of the vehicle will not be given to the driver who was involved in the original impoundment proceeding until the expiration of the impoundment period.",
      "depth_em": 1.0
    },
    {
      "label": "3",
      "text": "Prior to relinquishing the vehicle, the legal owner may require the registered owner to pay all towing and storage charges related to the impoundment and the administrative charges authorized under Section 22850.5 that were incurred by the legal owner in connection with obtaining the custody of the vehicle.",
      "depth_em": 1.0
    },
    {
      "label": "4",
      "text": "Any legal owner who knowingly releases or causes the release of a vehicle to a registered owner or the person in possession of the vehicle at the time of the impoundment or any agent of the registered owner in violation of this subdivision shall be guilty of a misdemeanor and subject to a civil penalty in the amount of two thousand dollars ($2,000).",
      "depth_em": 1.0
    },
    {
      "label": "5",
      "text": "The legal owner, registered owner, or person in possession of the vehicle shall not change or attempt to change the name of the legal owner or the registered owner on the records of the department until the vehicle is released from the impoundment.",
      "depth_em": 1.0
    },
    {
      "label": "g",
      "text": "Notwithstanding any other provision of this section, the registered owner and not the legal owner shall remain responsible for any towing and storage charges related to the impoundment and the administrative charges authorized under Section 22850.5 and any parking fines, penalties, and administrative fees incurred by the registered owner.",
      "depth_em": 0.0
    },
    {
      "label": "h",
      "text": "The law enforcement agency and the impounding agency, including any storage facility acting on behalf of the law enforcement agency or impounding agency, shall comply with this section and shall not be liable to the registered owner for the improper release of the vehicle to the legal owner or the legal owner’s agent if the release complies with this section. The legal owner shall indemnify and hold harmless a storage facility from any claims arising out of the release of the vehicle to the legal owner or the legal owner’s agent and from any damage to the vehicle after its release, including the reasonable costs associated with defending any such claims. A law enforcement agency shall not refuse to issue a release to a legal owner or the agent of a legal owner on the grounds that it previously issued a release.",
      "depth_em": 0.0
    }
  ],
  "history": {
    "raw": "(Amended by Stats. 2011, Ch. 536, Sec. 14. (AB 957) Effective January 1, 2012.)",
    "action": "Amended",
    "statutes_year": 2011,
    "chapter": "536",
    "section": "14",
    "bill_number": "AB 957",
    "effective_date": "2012-01-01",
    "operative_date": null
  },
  "op_statues": "2011",
  "op_chapter": "536",
  "op_section": "14",
  "source_url": "https://leginfo.legislature.ca.gov/faces/codes_displaySection.xhtml?sectionNum=21100.4.&lawCode=VEH",
  "source_path": "data/raw/ca_leginfo_pages/VEH/21100.4.html",
  "content_sha256": "a933595e33bda0b7cefd444460ea6c0352841867550f6c8bb5a9e46f04a64bd1",
  "parsed_at": "2026-05-09T18:32:19+00:00",
  "parser_version": "1"
}
